pyotf/__init__.py
pyotf/_version.py
pyotf/display.py
pyotf/labview.py
pyotf/microscope.py
pyotf/otf.py
pyotf/phaseretrieval.py
pyotf/utils.py
pyotf/zernike.py
pyotf-0.0.3.dist-info/LICENSE.md
pyotf-0.0.3.dist-info/METADATA
pyotf-0.0.3.dist-info/WHEEL
pyotf-0.0.3.dist-info/top_level.txt
pyotf-0.0.3.dist-info/RECORD
