Metadata-Version: 2.1
Name: pyotf
Version: 0.0.3
Summary: A python library for simulating and analyzing microscope point spread functions (PSFs)
Home-page: https://github.com/david-hoffman/pyOTF
Author: David Hoffman
Author-email: dave.p.hoffman@gmail.com
License: Apache V2.0
Platform: UNKNOWN
Classifier: Development Status :: 3 - Alpha
Classifier: Programming Language :: Python :: 3
Classifier: License :: OSI Approved :: Apache Software License
Classifier: Natural Language :: English
Classifier: Operating System :: OS Independent
Classifier: Topic :: Scientific/Engineering
Requires-Python: >=3.8
Requires-Dist: numpy
Requires-Dist: scipy
Requires-Dist: scikit-image
Requires-Dist: matplotlib
Requires-Dist: tifffile
Requires-Dist: dphtools
